LICENSE
MANIFEST.in
README.rst
pyproject.toml
setup.cfg
setup.py
django_mobile_detect.egg-info/PKG-INFO
django_mobile_detect.egg-info/SOURCES.txt
django_mobile_detect.egg-info/dependency_links.txt
django_mobile_detect.egg-info/requires.txt
django_mobile_detect.egg-info/top_level.txt
mobiledetect/__init__.py
mobiledetect/constants.py
mobiledetect/detection.py
mobiledetect/headers.py
mobiledetect/middleware.py
mobiledetect/tests.py
mobiledetect/user_agent.py